LICENSE
README.md
setup.py
investing_world_indices_scraper/__init__.py
investing_world_indices_scraper.egg-info/PKG-INFO
investing_world_indices_scraper.egg-info/SOURCES.txt
investing_world_indices_scraper.egg-info/dependency_links.txt
investing_world_indices_scraper.egg-info/requires.txt
investing_world_indices_scraper.egg-info/top_level.txt