Metadata-Version: 2.1
Name: investing-world-indices-scraper
Version: 1.0.0
Summary: A python library to scrape world indices on investing.com
Home-page: UNKNOWN
Author: DataKund
Author-email: datakund@gmail.com
License: Apache License 2.0
Keywords: investing.com world_indices stock_name stock price python bot_studio automation scraper
Platform: UNKNOWN
License-File: LICENSE
